Workbook
Name salario: 'APP'!$D$6
Name rendimento_carteira: 'APP'!$D$7
Name sugestao_investimento: 'APP'!$D$8
Name aporte: 'APP'!$D$11
Name anos: 'APP'!$D$12
Name taxa_mensal: 'APP'!$D$13
Name patrimonio_acumulado: 'APP'!$D$14
Name dividendos_mensais: 'APP'!$D$15
Name perfil: 'APP'!$C$26

Sheet APP
B2: Cofre Futuro Infantil | Simulador de Patrimônio & Dividendos para os Filhos
B3: Planejamento Financeiro de Longo Prazo e Criação de Renda Passiva
B5: CONFIGURAÇÕES
B6: Salário do Casal/Responsável | D6: 2000
B7: Rendimento da Carteira (ao mês) | D7: 0.006
B8: Sugestão de Investimento (30%) | D8: =salario*0.3
B10: INVESTIMENTO MENSAL & SIMULAÇÃO
B11: 1. Quanto investir por mês ? | D11: 200
B12: 2. Por Quantos Anos ? | D12: 5
B13: 3. Taxa de Rendimento mensal ? | D13: 0.01079
B14: 4. Patrimônio acumulado ? | D14: =FV(taxa_mensal; anos*12; -aporte)
B15: 5. Dividendos Mensais ? | D15: =patrimonio_acumulado*rendimento_carteira
B17: PROJEÇÃO DE CENÁRIOS (2 A 30 ANOS)
B18: Anos | C18: Horizonte / Descrição | D18: Patrimônio Acumulado | E18: Dividendo Mensal
B19: 2 | C19: Quanto em 2 Anos ? | D19: =FV(taxa_mensal; B19*12; -aporte) | E19: =D19*rendimento_carteira
B20: 5 | C20: Quanto em 5 Anos ? | D20: =FV(taxa_mensal; B20*12; -aporte) | E20: =D20*rendimento_carteira
B21: 10 | C21: Quanto em 10 Anos ? | D21: =FV(taxa_mensal; B21*12; -aporte) | E21: =D21*rendimento_carteira
B22: 20 | C22: Quanto em 20 Anos ? | D22: =FV(taxa_mensal; B22*12; -aporte) | E22: =D22*rendimento_carteira
B23: 30 | C23: Quanto em 30 Anos ? | D23: =FV(taxa_mensal; B23*12; -aporte) | E23: =D23*rendimento_carteira
B25: DIVISÃO DO APORTE POR PERFIL
B26: PERFIL SELECIONADO: | C26: Moderado
B27: VALOR INVESTIDO/MÊS: | C27: =aporte
B29: TIPO DE FII | C29: Percentual Sugerido | D29: Valores (R$)
B30: PAPEL | C30: =VLOOKUP(perfil&"-"&B30; APOIO!$A$2:$D$19; 4; FALSE) | D30: =C27*C30
B31: TIJOLO | C31: =VLOOKUP(perfil&"-"&B31; APOIO!$A$2:$D$19; 4; FALSE) | D31: =C27*C31
B32: HÍBRIDOS | C32: =VLOOKUP(perfil&"-"&B32; APOIO!$A$2:$D$19; 4; FALSE) | D32: =C27*C32
B33: FOFs | C33: =VLOOKUP(perfil&"-"&B33; APOIO!$A$2:$D$19; 4; FALSE) | D33: =C27*C33
B34: DESENVOLVIMENTO | C34: =VLOOKUP(perfil&"-"&B34; APOIO!$A$2:$D$19; 4; FALSE) | D34: =C27*C34
B35: HOTELARIAS | C35: =VLOOKUP(perfil&"-"&B35; APOIO!$A$2:$D$19; 4; FALSE) | D35: =C27*C35
B36: TOTAL | C36: =SUM(C30:C35) | D36: =SUM(D30:D35)

Sheet APOIO
A1: CHAVE | B1: PERFIL | C1: TIPO DE FII | D1: %
A2: =B2&"-"&C2 | B2: Conservador | C2: PAPEL | D2: 0.3
A3: =B3&"-"&C3 | B3: Conservador | C3: TIJOLO | D3: 0.5
A4: =B4&"-"&C4 | B4: Conservador | C4: HÍBRIDOS | D4: 0.1
A5: =B5&"-"&C5 | B5: Conservador | C5: FOFs | D5: 0.1
A6: =B6&"-"&C6 | B6: Conservador | C6: DESENVOLVIMENTO | D6: 0
A7: =B7&"-"&C7 | B7: Conservador | C7: HOTELARIAS | D7: 0
A8: =B8&"-"&C8 | B8: Moderado | C8: PAPEL | D8: 0.32
A9: =B9&"-"&C9 | B9: Moderado | C9: TIJOLO | D9: 0.35
A10: =B10&"-"&C10 | B10: Moderado | C10: HÍBRIDOS | D10: 0.08
A11: =B11&"-"&C11 | B11: Moderado | C11: FOFs | D11: 0.05
A12: =B12&"-"&C12 | B12: Moderado | C12: DESENVOLVIMENTO | D12: 0.1
A13: =B13&"-"&C13 | B13: Moderado | C13: HOTELARIAS | D13: 0.1
... A19: =B19&"-"&C19 | B19: Agressivo | C19: HOTELARIAS | D19: 0.1
